README.txt
setup.py
collective/__init__.py
collective.collage.rssdocument.egg-info/PKG-INFO
collective.collage.rssdocument.egg-info/SOURCES.txt
collective.collage.rssdocument.egg-info/dependency_links.txt
collective.collage.rssdocument.egg-info/entry_points.txt
collective.collage.rssdocument.egg-info/namespace_packages.txt
collective.collage.rssdocument.egg-info/not-zip-safe
collective.collage.rssdocument.egg-info/requires.txt
collective.collage.rssdocument.egg-info/top_level.txt
collective/collage/__init__.py
collective/collage/rssdocument/__init__.py
collective/collage/rssdocument/configure.zcml
collective/collage/rssdocument/rssdocument.pt
collective/collage/rssdocument/tests.py
collective/collage/rssdocument/version.txt
collective/collage/rssdocument/view.py
docs/HISTORY.txt
docs/INSTALL.txt
docs/LICENSE.GPL
docs/LICENSE.txt