Metadata-Version: 1.0
Name: collective.collage.rssdocument
Version: 0.2
Summary: Add-on that allows displaying RSSDocuments inside a Collage.
Home-page: http://svn.plone.org/svn/collective/collective.collage.rssdocument
Author: Noe Nieto
Author-email: desarrollo@iservices.com.mx
License: LGPL
Keywords: collage plone iservices rss rssdocument
Platform: UNKNOWN
Classifier: Framework :: Plone
Classifier: Programming Language :: Python
